Metadata-Version: 2.1
Name: path-append
Version: 0.1.1
Summary: This Package append parent path
Home-page: UNKNOWN
Author-email: no_one@gmail.com
License: UNKNOWN
Platform: UNKNOWN
